wsgirouter3_weasyprint.py
wsgirouter3_weasyprint-0.1.2.dist-info/LICENSE
wsgirouter3_weasyprint-0.1.2.dist-info/METADATA
wsgirouter3_weasyprint-0.1.2.dist-info/WHEEL
wsgirouter3_weasyprint-0.1.2.dist-info/top_level.txt
wsgirouter3_weasyprint-0.1.2.dist-info/RECORD
