Metadata-Version: 2.1
Name: wsgirouter3-weasyprint
Version: 0.1.2
Summary: WSGI routing library weasyprint plugin
Home-page: https://github.com/andruskutt/wsgirouter3-weasyprint
Author: Andrus Kütt
Author-email: andrus.kuett@gmail.com
License: MIT
Keywords: web services
Classifier: Environment :: Web Environment
Classifier: Intended Audience :: Developers
Classifier: License :: OSI Approved :: MIT License
Classifier: Operating System :: OS Independent
Classifier: Programming Language :: Python :: 3
Classifier: Programming Language :: Python :: 3.7
Classifier: Programming Language :: Python :: 3.8
Classifier: Programming Language :: Python :: 3.9
Classifier: Programming Language :: Python :: 3.10
Classifier: Topic :: Internet :: WWW/HTTP
Classifier: Topic :: Internet :: WWW/HTTP :: WSGI :: Application
Requires-Python: >=3.7
License-File: LICENSE
